README.rst
setup.py
og_fetcher/__init__.py
og_fetcher/fetch.py
og_fetcher/parse.py
og_fetcher.egg-info/PKG-INFO
og_fetcher.egg-info/SOURCES.txt
og_fetcher.egg-info/dependency_links.txt
og_fetcher.egg-info/top_level.txt