Metadata-Version: 1.0
Name: og-fetcher
Version: 0.3
Summary: Open Graph Fetcher
Home-page: https://github.com/mnkuran/og-fetcher
Author: Mahmut Kuran
Author-email: mahmutkuran@hotmail.com
License: MIT
Platform: UNKNOWN
